Python_dependency_confusion_attacks/__init__.py
Python_dependency_confusion_attacks-0.0.0.dist-info/METADATA
Python_dependency_confusion_attacks-0.0.0.dist-info/WHEEL
Python_dependency_confusion_attacks-0.0.0.dist-info/top_level.txt
Python_dependency_confusion_attacks-0.0.0.dist-info/RECORD
