Metadata-Version: 2.1
Name: Python-dependency-confusion-attacks
Version: 0.0.0
Summary: Dependency confiuse Attack
Home-page: UNKNOWN
Author: techghoshal
Author-email: techghoshal@gmail.com
License: UNKNOWN
Platform: UNKNOWN
Requires-Dist: discord
Requires-Dist: requests
